cloudspark/__init__.py
cloudspark/aws_connect.py
cloudspark/lambda_connect.py
cloudspark/s3_connect.py
cloudspark/utils.py
cloudspark-2.0.1.dist-info/LICENSE
cloudspark-2.0.1.dist-info/METADATA
cloudspark-2.0.1.dist-info/WHEEL
cloudspark-2.0.1.dist-info/top_level.txt
cloudspark-2.0.1.dist-info/RECORD
