Metadata-Version: 2.1
Name: cloudspark
Version: 2.0.1
Summary: The CloudsPark package is designed to simplify the management of AWS S3 and Lambda services. Whether you're working on the frontend or backend, CloudSpark provides an intuitive interface to generate presigned URLs and handle file uploads seamlessly.
Home-page: https://github.com/muhammedrahil/cloudspark
Author: Muhammed Rahil M
Author-email: muhammedrahilmadathingal@gmail.com
License: UNKNOWN
Keywords: python,aws,s3,presigned urls,file uploads
Platform: UNKNOWN
Classifier: Development Status :: 1 - Planning
Classifier: Intended Audience :: Developers
Classifier: Programming Language :: Python :: 3.11
Classifier: Operating System :: OS Independent
Classifier: License :: OSI Approved :: MIT License
License-File: LICENSE
Requires-Dist: boto3
